mixture_of_experts/__init__.py
mixture_of_experts/mixture_of_experts.py
mixture_of_experts-0.2.3.dist-info/LICENSE
mixture_of_experts-0.2.3.dist-info/METADATA
mixture_of_experts-0.2.3.dist-info/WHEEL
mixture_of_experts-0.2.3.dist-info/top_level.txt
mixture_of_experts-0.2.3.dist-info/RECORD
