Metadata-Version: 2.1
Name: mixture-of-experts
Version: 0.2.3
Summary: Sparsely-Gated Mixture of Experts for Pytorch
Home-page: https://github.com/lucidrains/mixture-of-experts
Author: Phil Wang
Author-email: lucidrains@gmail.com
License: MIT
Keywords: artificial intelligence,deep learning,transformers,mixture of experts
Classifier: Development Status :: 4 - Beta
Classifier: Intended Audience :: Developers
Classifier: Topic :: Scientific/Engineering :: Artificial Intelligence
Classifier: License :: OSI Approved :: MIT License
Classifier: Programming Language :: Python :: 3.6
License-File: LICENSE
Requires-Dist: torch
